n7gg/__init__.py
n7gg/__version__.py
n7gg/app.py
n7gg-0.dist-info/LICENSE
n7gg-0.dist-info/WHEEL
n7gg-0.dist-info/METADATA
n7gg-0.dist-info/RECORD
