Metadata-Version: 2.1
Name: n7gg
Version: 0
Summary: URL shortener
Home-page: https://github.com/jreese/n7gg
Author: John Reese
Author-email: john@noswap.com
Requires-Python: >=3.10
Classifier: Intended Audience :: Developers
Classifier: License :: OSI Approved :: MIT License
Classifier: Topic :: Utilities
Classifier: Typing :: Typed
Requires-Dist: sanic >= 22
